Metadata-Version: 2.1
Name: smarttitletool
Version: 1.0.0
Summary: A simple tool for flexible smart title case formatting
Author: Khalid Sulaiman Al-Mulaify
Author-email: khalidmfy@gmail.com
Keywords: title case formatter smart title tool string manipulation
Classifier: Programming Language :: Python :: 3
Classifier: License :: OSI Approved :: MIT License
Classifier: Operating System :: OS Independent
Requires-Python: >=3.6
